gaze/__init__.py
gaze/pipes.py
gaze/engine/__init__.py
gaze/engine/base_node.py
gaze/engine/sequential.py
gaze/engine/source_node.py
gaze/nodes/__init__.py
gaze/nodes/core.py
gaze/nodes/wrappers.py
gaze/utils/__init__.py
gaze/utils/vis_utils.py
gaze-0.0.3.dist-info/METADATA
gaze-0.0.3.dist-info/RECORD
gaze-0.0.3.dist-info/WHEEL
gaze-0.0.3.dist-info/top_level.txt
